{"cameraMode":{"drawMode":0,"name":"Shaded","section":"Shading Mode"},"sceneLighting":true,"audioPlay":false,"sceneViewState":{"showFog":true,"showMaterialUpdate":false,"showSkybox":true,"showFlares":true,"showImageEffects":true,"showParticleSystems":true},"in2DMode":false,"pivot":{"x":13.119209289550782,"y":3.895747661590576,"z":-1.165663719177246},"rotation":{"x":-0.027529744431376458,"y":-0.9080848693847656,"z":0.059929411858320239,"w":-0.4135609269142151},"size":8.731223106384278,"orthographic":false}